{"is_source_file": true, "format": "JavaScript (React JSX)", "description": "React component 'BearTable' displays a table of bear pose records, fetching data from a configurable API endpoint with auto-refresh and loading/error states.", "external_files": ["react"], "external_methods": ["React.useEffect", "React.useMemo", "React.useRef", "React.useState"], "published": ["BearTable"], "classes": [], "methods": [{"name": "fetchBears", "description": "Fetches bear data from the API endpoint, handling abort signals and response parsing."}, {"name": "formatTimestamp(ts)", "description": "Formats ISO timestamp strings into localized date/time strings.", "scope": "", "scopeKind": ""}, {"name": "BearTable()", "scope": "", "scopeKind": "", "description": "unavailable"}], "calls": ["React.useEffect", "React.useMemo", "React.useRef", "React.useState", "fetch", "formatTimestamp", "setInterval", "clearInterval", "setLoading", "setError", "setBears", "setLastUpdated"], "search-terms": ["BearTable", "react_component_bear_data_table", "auto_refresh_bears", "fetch_bears_component", "environment_variable_bear_api"], "state": 2, "file_id": 13, "knowledge_revision": 38, "git_revision": "10cc06c5763e866ab17e37a51117ad5cf3c813dd", "revision_history": [{"26": ""}, {"33": "cbc8856162b7189c86fe85cf2b5d8ba49be68801"}, {"34": "978f501133db88f6424511eb5d7b2b7a51f057d8"}, {"35": "978f501133db88f6424511eb5d7b2b7a51f057d8"}, {"37": "10cc06c5763e866ab17e37a51117ad5cf3c813dd"}, {"38": "10cc06c5763e866ab17e37a51117ad5cf3c813dd"}], "ctags": [{"_type": "tag", "name": "3", "path": "/home/kavia/workspace/code-generation/bear-data-viewer-157938-157961/react_frontend/src/components/BearTable.jsx", "pattern": "/^            <td colSpan={3} className=\"error-cell\">$/", "language": "JavaScript", "kind": "field", "scope": "BearTable.AnonymousClass821f2f7d0101", "scopeKind": "class"}, {"_type": "tag", "name": "3", "path": "/home/kavia/workspace/code-generation/bear-data-viewer-157938-157961/react_frontend/src/components/BearTable.jsx", "pattern": "/^            <td colSpan={3} className=\"muted-cell\">$/", "language": "JavaScript", "kind": "field", "scope": "BearTable.AnonymousClass821f2f7d0201", "scopeKind": "class"}, {"_type": "tag", "name": "API_URL", "path": "/home/kavia/workspace/code-generation/bear-data-viewer-157938-157961/react_frontend/src/components/BearTable.jsx", "pattern": "/^const API_URL = process.env.REACT_APP_BEAR_API_URL || DEFAULT_API_URL;$/", "language": "JavaScript", "kind": "constant"}, {"_type": "tag", "name": "BearTable", "path": "/home/kavia/workspace/code-generation/bear-data-viewer-157938-157961/react_frontend/src/components/BearTable.jsx", "pattern": "/^function BearTable() {$/", "language": "JavaScript", "kind": "function", "signature": "()"}, {"_type": "tag", "name": "DEFAULT_API_URL", "path": "/home/kavia/workspace/code-generation/bear-data-viewer-157938-157961/react_frontend/src/components/BearTable.jsx", "pattern": "/^const DEFAULT_API_URL =$/", "language": "JavaScript", "kind": "constant"}, {"_type": "tag", "name": "ENV_REFRESH_SECS", "path": "/home/kavia/workspace/code-generation/bear-data-viewer-157938-157961/react_frontend/src/components/BearTable.jsx", "pattern": "/^const ENV_REFRESH_SECS = Number(process.env.REACT_APP_REFRESH_INTERVAL_SECONDS);$/", "language": "JavaScript", "kind": "constant"}, {"_type": "tag", "name": "REFRESH_INTERVAL_MS", "path": "/home/kavia/workspace/code-generation/bear-data-viewer-157938-157961/react_frontend/src/components/BearTable.jsx", "pattern": "/^const REFRESH_INTERVAL_MS =$/", "language": "JavaScript", "kind": "constant"}, {"_type": "tag", "name": "formatTimestamp", "path": "/home/kavia/workspace/code-generation/bear-data-viewer-157938-157961/react_frontend/src/components/BearTable.jsx", "pattern": "/^function formatTimestamp(ts) {$/", "language": "JavaScript", "kind": "function", "signature": "(ts)"}], "hash": "c3d7a41977bd043c1f7391b826b84938", "format-version": 4, "code-base-name": "react_frontend", "filename": "react_frontend/src/components/BearTable.jsx", "fields": [{"name": "<td colSpan={3} className=\"error-cell\">", "scope": "BearTable.AnonymousClass821f2f7d0101", "scopeKind": "class", "description": "unavailable"}, {"name": "<td colSpan={3} className=\"muted-cell\">", "scope": "BearTable.AnonymousClass821f2f7d0201", "scopeKind": "class", "description": "unavailable"}]}